heater/__init__.py
heater/__main__.py
heater/code.py
heater/constants.py
heater/generators.py
heater/utils.py
heater/ux.py
heater/boilerplate/discord.py
heater/boilerplate/dpy_extension.py
heater/boilerplate/hikari.py
heater/boilerplate/hikari_extension.py
discord_heater-0.0.1.dist-info/LICENSE
discord_heater-0.0.1.dist-info/METADATA
discord_heater-0.0.1.dist-info/WHEEL
discord_heater-0.0.1.dist-info/entry_points.txt
discord_heater-0.0.1.dist-info/top_level.txt
discord_heater-0.0.1.dist-info/RECORD
