Metadata-Version: 2.1
Name: discord-heater
Version: 0.0.1
Summary: UNKNOWN
Home-page: https://github.com/ahnaf-zamil/heater
Author: K.M Ahnaf Zamil
Author-email: ahnaf@ahnafzamil.com
License: UNKNOWN
Platform: UNKNOWN
Classifier: Programming Language :: Python :: 3
Classifier: License :: OSI Approved :: MIT License
Classifier: Operating System :: OS Independent
Classifier: Programming Language :: Python :: 3.8
Requires-Python: >=3.8
